reframe/__init__.py
reframe_py-0.0.4.dist-info/LICENSE
reframe_py-0.0.4.dist-info/METADATA
reframe_py-0.0.4.dist-info/WHEEL
reframe_py-0.0.4.dist-info/RECORD
