Metadata-Version: 2.1
Name: reframe-py
Version: 0.0.4
Summary: Create, run and manage your intelligent LLM agents on dataframes.
Home-page: https://reframe.is/docs/
Keywords: ReframeAI,agents,dataframes,client
Author: ReframeAI Team
Author-email: pypi@reframe.is
Requires-Python: >=3.9,<4.0
Classifier: Programming Language :: Python :: 3
Classifier: Programming Language :: Python :: 3.9
Classifier: Programming Language :: Python :: 3.10
Classifier: Programming Language :: Python :: 3.11
Requires-Dist: aiofiles (>=23.2.1,<24.0.0)
Requires-Dist: betterproto (==2.0.0b4)
Requires-Dist: black (>=23.3.0,<24.0.0)
Requires-Dist: grpcio (>=1.46.0,<2.0.0)
Requires-Dist: httpx[http2] (>=0.23.0,<0.24.0)
Requires-Dist: jinja2 (>=3.1.2,<4.0.0)
Requires-Dist: loguru (>=0.5.3,<0.6.0)
Requires-Dist: nest-asyncio (>=1.5.5,<2.0.0)
Requires-Dist: pyarrow (>=12.0.1,<13.0.0)
Requires-Dist: pydantic (>=2.3.0,<3.0.0)
Requires-Dist: pydantic-settings (>=2.0.3,<3.0.0)
Requires-Dist: python-decouple (>=3.8,<4.0)
Requires-Dist: python-dotenv (>=1.0.0,<2.0.0)
Requires-Dist: python-multipart (>=0.0.6,<0.0.7)
Requires-Dist: requests (==2.29.0)
Requires-Dist: ruff (>=0.0.265,<0.0.266)
Requires-Dist: tabulate (>=0.9.0,<0.10.0)
Requires-Dist: tiktoken (>=0.4.0,<0.5.0)
Requires-Dist: tqdm (>=4.56.0,<5.0.0)
Requires-Dist: transformers (>=4.30.2,<5.0.0)
Requires-Dist: twine (>=4.0.2,<5.0.0)
Requires-Dist: typing-extensions (>=4.0.0,<5.0.0)
Requires-Dist: unstructured (>=0.6.4,<0.7.0)
Requires-Dist: uuid (>=1.30,<2.0)
Requires-Dist: uuid6 (>=2023.5.2,<2024.0.0)
Requires-Dist: validators (>=0.21.2,<0.22.0)
Requires-Dist: werkzeug (>=2.3.7,<3.0.0)
Project-URL: Repository, https://github.com/peterwnjenga/reframe
